{
	"boot": {
	  "use_connectivity_service": true,
	  "start_connectivity_service": true,
	  "connectivity_service_host": "localhost",
	  "connectivity_service_port": 15432,
	  "opmon_impl": "cern",
	  "ers_impl":"cern",
	  "op_env": "dvargas-perf"
	}, 
	"readout": {
	  "thread_pinning_file":"/nfs/home/dvargas/DUNE-SW/dunedaq-latest/sourcecode/performancetest/cpupins/cpupin-eth-basic.json",
	  "default_data_file": "wibeth/wibeth_output_ALL_ZEROS.bin",
	  "clock_speed_hz": 62500000,
	  "data_rate_slowdown_factor": 1,
	  "use_fake_cards": true
	},
	"trigger": {
	  "trigger_window_before_ticks": 1000,
	  "trigger_window_after_ticks": 1000,
	  "trigger_rate_hz": 0.1
	}
  }